<?xml version="1.0" encoding="utf-8" ?>
<dwsync>
<file name="civi-helper.php" server="citymody.ftp.tools//citymody.com/www/" local="133295620237525871" remote="133295620200000000" Dst="2" />
<file name="civi-template-hooks.php" server="citymody.ftp.tools//citymody.com/www/" local="133295267484338267" remote="133295268600000000" Dst="2" />
<file name="civi-util.php" server="citymody.ftp.tools//citymody.com/www/" local="133270743516926688" remote="133292281800000000" Dst="2" />
<file name="class-civi-breadcrumb.php" server="citymody.ftp.tools//citymody.com/www/" local="133270743516936686" remote="133292281800000000" Dst="2" />
<file name="class-civi-ajax.php" server="citymody.ftp.tools//citymody.com/www/" local="133270743516936686" remote="133292281800000000" Dst="2" />
<file name="class-civi-capability.php" server="citymody.ftp.tools//citymody.com/www/" local="133270743516946687" remote="133292281800000000" Dst="2" />
<file name="class-civi-core.php" server="citymody.ftp.tools//citymody.com/www/" local="133270743516956687" remote="133292281800000000" Dst="2" />
<file name="class-civi-deactivator.php" server="citymody.ftp.tools//citymody.com/www/" local="133270743516956687" remote="133292281800000000" Dst="2" />
<file name="class-civi-footer.php" server="citymody.ftp.tools//citymody.com/www/" local="133270743516966683" remote="133292281800000000" Dst="2" />
<file name="class-civi-shortcodes.php" server="citymody.ftp.tools//citymody.com/www/" local="133270743516966683" remote="133292281800000000" Dst="2" />
<file name="class-civi-template-loader.php" server="citymody.ftp.tools//citymody.com/www/" local="133295267659532497" remote="133295269200000000" Dst="2" />
<file name="class-civi-user.php" server="citymody.ftp.tools//citymody.com/www/" local="133270743516986688" remote="133292281800000000" Dst="2" />
<file name="class-civi-shortcodes.php" server="citymody.ftp.tools//citymody.com/" local="133299213279449610" remote="133306374600000000" Dst="2" />
<file name="class-civi-template-loader.php" server="citymody.ftp.tools//citymody.com/" local="133306369316075090" remote="133306374600000000" Dst="2" />
<file name="civi-template-hooks.php" server="citymody.ftp.tools//citymody.com/" local="133315583059674730" remote="133315584000000000" Dst="2" />
<file name="civi-helper.php" server="citymody.ftp.tools//citymody.com/" local="133318269077802440" remote="133318269000000000" Dst="2" />
<file name="class-civi-ajax.php" server="citymody.ftp.tools//citymody.com/" local="133315575813531195" remote="133315584000000000" Dst="2" />
<file name="class-civi-core.php" server="citymody.ftp.tools//citymody.com/" local="133306369397516039" remote="133306374600000000" Dst="2" />
<file name="civi-util.php" server="citymody.ftp.tools//citymody.com/" local="133270743516926688" remote="133306374600000000" Dst="2" />
<file name="class-civi-breadcrumb.php" server="citymody.ftp.tools//citymody.com/" local="133270743516936686" remote="133306374600000000" Dst="2" />
<file name="class-civi-capability.php" server="citymody.ftp.tools//citymody.com/" local="133270743516946687" remote="133306374600000000" Dst="2" />
<file name="class-civi-deactivator.php" server="citymody.ftp.tools//citymody.com/" local="133270743516956687" remote="133306374600000000" Dst="2" />
<file name="class-civi-footer.php" server="citymody.ftp.tools//citymody.com/" local="133270743516966683" remote="133306374600000000" Dst="2" />
<file name="class-civi-user.php" server="citymody.ftp.tools//citymody.com/" local="133270743516986688" remote="133306374600000000" Dst="2" />
</dwsync>